README.md
setup.py
example_pkg/__init__.py
example_pkg/example.py
example_pkg02031997.egg-info/PKG-INFO
example_pkg02031997.egg-info/SOURCES.txt
example_pkg02031997.egg-info/dependency_links.txt
example_pkg02031997.egg-info/top_level.txt