Metadata-Version: 2.1
Name: example-pkg02031997
Version: 0.0.1
Summary: A small example package
Home-page: UNKNOWN
Author: Narendra
Author-email: narendra02031997@gmail.com
License: UNKNOWN
Platform: UNKNOWN
Classifier: Programming Language :: Python :: 3
Classifier: License :: OSI Approved :: MIT License
Classifier: Operating System :: OS Independent
